LICENSE.txt
MANIFEST.in
README.rst
README.txt
scrapyredirect.py
setup.py
scrapy_redirect.egg-info/PKG-INFO
scrapy_redirect.egg-info/SOURCES.txt
scrapy_redirect.egg-info/dependency_links.txt
scrapy_redirect.egg-info/requires.txt
scrapy_redirect.egg-info/top_level.txt