Metadata-Version: 1.1
Name: scrapy-redirect
Version: 0.1.0
Summary: Restrict authorized Scrapy redirections to the website start_urls
Home-page: http://github.com/mapado/scrapy-redirect
Author: Balthazar Rouberol
Author-email: balthazar@mapado.com
License: The MIT License (MIT)
Keywords: scrapy crawl scraping
Platform: Any
Classifier: Development Status :: 4 - Beta
Classifier: Environment :: No Input/Output (Daemon)
Classifier: License :: OSI Approved :: MIT License
Classifier: Operating System :: OS Independent
Classifier: Programming Language :: Python
